groundwork_validation/__init__.py
groundwork_validation/version.py
groundwork_validation/patterns/__init__.py
groundwork_validation/patterns/gw_cmd_validators_pattern/__init__.py
groundwork_validation/patterns/gw_cmd_validators_pattern/gw_cmd_validators_pattern.py
groundwork_validation/patterns/gw_db_validators_pattern/__init__.py
groundwork_validation/patterns/gw_db_validators_pattern/gw_db_validators_pattern.py
groundwork_validation/patterns/gw_file_validators_pattern/__init__.py
groundwork_validation/patterns/gw_file_validators_pattern/gw_file_validators_pattern.py
groundwork_validation/patterns/gw_validators_pattern/__init__.py
groundwork_validation/patterns/gw_validators_pattern/gw_validators_pattern.py
groundwork_validation/plugins/__init__.py
groundwork_validation/plugins/gw_db_validator/__init__.py
groundwork_validation/plugins/gw_db_validator/gw_db_validator.py
groundwork_validation/recipes/__init__.py
groundwork_validation-0.1.5.dist-info/DESCRIPTION.rst
groundwork_validation-0.1.5.dist-info/METADATA
groundwork_validation-0.1.5.dist-info/RECORD
groundwork_validation-0.1.5.dist-info/WHEEL
groundwork_validation-0.1.5.dist-info/entry_points.txt
groundwork_validation-0.1.5.dist-info/metadata.json
groundwork_validation-0.1.5.dist-info/top_level.txt
