Metadata-Version: 2.0
Name: groundwork-validation
Version: 0.1.5
Summary: Package for hosting groundwork apps and plugins like groundwork_validation_app or groundwork_validation_plugin.
Home-page: http://groundwork_validation.readthedocs.org
Author: team useblocks
Author-email: info@useblocks.com
License: MIT license
Platform: any
Classifier: Development Status :: 3 - Alpha
Classifier: Environment :: Console
Classifier: Intended Audience :: Developers
Classifier: License :: OSI Approved :: MIT License
Classifier: Operating System :: OS Independent
Classifier: Programming Language :: Python
Classifier: Programming Language :: Python :: 3
Classifier: Programming Language :: Python :: 3.4
Classifier: Programming Language :: Python :: 3.5
Requires-Dist: groundwork
Requires-Dist: groundwork-database
